XSDreg/XSDreg.py
XSDreg/__init__.py
XSDreg-1.0.1.dist-info/METADATA
XSDreg-1.0.1.dist-info/RECORD
XSDreg-1.0.1.dist-info/WHEEL
XSDreg-1.0.1.dist-info/top_level.txt
